LICENSE
README.md
setup.cfg
setup.py
setup_pip.py
molplotly/__init__.py
molplotly/main.py
molplotly.egg-info/PKG-INFO
molplotly.egg-info/SOURCES.txt
molplotly.egg-info/dependency_links.txt
molplotly.egg-info/requires.txt
molplotly.egg-info/top_level.txt
tests/__init__.py
tests/test_add_molecules.py