Metadata-Version: 2.1
Name: molplotly
Version: 1.1.2
Summary: plotly add-on to render molecule images on mouseover
Home-page: https://github.com/wjm41/molplotly
Author: William McCorkindale
License: Apache License 2.0
Platform: UNKNOWN
Classifier: Programming Language :: Python :: 3.8
Classifier: Programming Language :: Python :: 3.9
Classifier: Programming Language :: Python :: 3.10
Classifier: Topic :: Scientific/Engineering
Provides-Extra: test
License-File: LICENSE
